[
  {
    "Id": "d6cfa45f-a617-45b1-bb65-50144219b1af",
    "Title": "\u0414\u043E\u043A\u0443\u043C\u0435\u043D\u0442 2",
    "Description": null,
    "FileName": "file2.pdf",
    "UploadDate": "2026-02-18T06:41:51.402567Z",
    "UpdatedAt": null,
    "UserId": null,
    "User": null,
    "CategoryId": null,
    "Category": null
  },
  {
    "Id": "764cf5a7-8db8-4724-a808-e3c99725d9eb",
    "Title": "kniga",
    "Description": null,
    "FileName": "\u043A\u043D\u0438\u0433\u0430",
    "UploadDate": "2026-02-17T18:56:29.0028143Z",
    "UpdatedAt": null,
    "UserId": null,
    "User": null,
    "CategoryId": null,
    "Category": null
  },
  {
    "Id": "be1d1529-f167-4a61-b61c-dc7ea7cd7a11",
    "Title": "\u0414\u043E\u043A\u0443\u043C\u0435\u043D\u0442 1",
    "Description": null,
    "FileName": "file1.pdf",
    "UploadDate": "2026-02-18T06:41:51.3983439Z",
    "UpdatedAt": null,
    "UserId": null,
    "User": null,
    "CategoryId": null,
    "Category": null
  },
  {
    "Id": "62501c1f-438d-4c97-a9a3-779c739e3a3d",
    "Title": "\u0414\u043E\u043A\u0443\u043C\u0435\u043D\u0442 2",
    "Description": null,
    "FileName": "file2.pdf",
    "UploadDate": "2026-02-18T06:41:33.0980016Z",
    "UpdatedAt": null,
    "UserId": null,
    "User": null,
    "CategoryId": null,
    "Category": null
  },
  {
    "Id": "26e36659-a4b3-4a18-93c9-33504e929dd7",
    "Title": "ff",
    "Description": null,
    "FileName": "ff",
    "UploadDate": "2026-02-18T06:37:17.913798Z",
    "UpdatedAt": null,
    "UserId": null,
    "User": null,
    "CategoryId": null,
    "Category": null
  },
  {
    "Id": "63521e89-b00e-4888-b3c6-2a0c05acfde9",
    "Title": "test",
    "Description": null,
    "FileName": "test",
    "UploadDate": "2026-02-17T19:00:13.3802694Z",
    "UpdatedAt": null,
    "UserId": null,
    "User": null,
    "CategoryId": null,
    "Category": null
  },
  {
    "Id": "71bd209d-6bce-4447-934c-d640d7ce5fda",
    "Title": "\u043F\u0430\u0432\u043F\u0430",
    "Description": null,
    "FileName": "\u0430\u0432\u044B\u0430",
    "UploadDate": "2026-02-18T06:00:48.0788279Z",
    "UpdatedAt": null,
    "UserId": null,
    "User": null,
    "CategoryId": null,
    "Category": null
  }
]